li_scrapi/__init__.py
li_scrapi/async_linkedin.py
li_scrapi/client.py
li_scrapi/cookie_repository.py
li_scrapi/linkedin.py
li_scrapi/linkedin_api.py
li_scrapi/utils/__init__.py
li_scrapi/utils/_base_linkedin.py
li_scrapi/utils/api_builder.py
li_scrapi/utils/errors.py
li_scrapi/utils/helpers.py
li_scrapi/utils/query_options.py
li_scrapi/utils/schemas.py
li_scrapi/utils/settings.py
li_scrapi-1.0.0.dist-info/LICENSE
li_scrapi-1.0.0.dist-info/METADATA
li_scrapi-1.0.0.dist-info/WHEEL
li_scrapi-1.0.0.dist-info/RECORD
