Metadata-Version: 2.1
Name: li_scrapi
Version: 1.0.0
Summary: Scraping API for LinkedIn, Built on the back of linkedin_api by Tom Quirk
Author: Khalid Al-Awady
Author-email: pipes_and_bottles@protonmail.com
Requires-Python: >=3.10,<4.0
Classifier: Programming Language :: Python :: 3
Classifier: Programming Language :: Python :: 3.10
Classifier: Programming Language :: Python :: 3.11
Classifier: Programming Language :: Python :: 3.12
Requires-Dist: aiolimiter (>=1.1.0,<2.0.0)
Requires-Dist: beautifulsoup4 (>=4.12.3,<5.0.0)
Requires-Dist: email-validator (>=2.2.0,<3.0.0)
Requires-Dist: httpx (>=0.27.0,<0.28.0)
Requires-Dist: loguru (>=0.7.2,<0.8.0)
Requires-Dist: lxml (>=5.2.2,<6.0.0)
Requires-Dist: pycountry (>=24.6.1,<25.0.0)
Requires-Dist: pydantic (>=2.8.2,<3.0.0)
Requires-Dist: pydantic-extra-types (>=2.9.0,<3.0.0)
Requires-Dist: tenacity (>=8.4.2,<9.0.0)
